Metadata-Version: 2.1
Name: jsonschema
Version: 4.12.0
Summary: An implementation of JSON Schema validation for Python
Project-URL: Homepage, https://github.com/python-jsonschema/jsonschema
Project-URL: Documentation, https://python-jsonschema.readthedocs.io/
Project-URL: Issues, https://github.com/python-jsonschema/jsonschema/issues/
Project-URL: Funding, https://github.com/sponsors/Julian
Project-URL: Tidelift, https://tidelift.com/subscription/pkg/pypi-jsonschema?utm_source=pypi-jsonschema&utm_medium=referral&utm_campaign=pypi-link
Project-URL: Changelog, https://github.com/python-jsonschema/jsonschema/blob/main/CHANGELOG.rst
Project-URL: Source, https://github.com/python-jsonschema/jsonschema
Author: Julian Berman
Author-email: Julian+jsonschema@GrayVines.com
License: MIT
Keywords: data validation,json,jsonschema,validation
Classifier: Development Status :: 5 - Production/Stable
Classifier: Intended Audience :: Developers
Classifier: License :: OSI Approved :: MIT License
Classifier: Operating System :: OS Independent
Classifier: Programming Language :: Python
Classifier: Programming Language :: Python :: 3.7
Classifier: Programming Language :: Python :: 3.8
Classifier: Programming Language :: Python :: 3.9
Classifier: Programming Language :: Python :: 3.10
Classifier: Programming Language :: Python :: 3.11
Classifier: Programming Language :: Python :: Implementation :: CPython
Classifier: Programming Language :: Python :: Implementation :: PyPy
Requires-Python: >=3.7
Requires-Dist: attrs>=17.4.0
Requires-Dist: importlib-metadata; python_version < '3.8'
Requires-Dist: importlib-resources>=1.4.0; python_version < '3.9'
Requires-Dist: pkgutil-resolve-name>=1.3.10; python_version < '3.9'
Requires-Dist: pyrsistent!=0.17.0,!=0.17.1,!=0.17.2,>=0.14.0
Requires-Dist: typing-extensions; python_version < '3.8'
Provides-Extra: format
Requires-Dist: fqdn; extra == 'format'
Requires-Dist: idna; extra == 'format'
Requires-Dist: isoduration; extra == 'format'
Requires-Dist: jsonpointer>1.13; extra == 'format'
Requires-Dist: rfc3339-validator; extra == 'format'
Requires-Dist: rfc3987; extra == 'format'
Requires-Dist: uri-template; extra == 'format'
Requires-Dist: webcolors>=1.11; extra == 'format'
Provides-Extra: format-nongpl
Requires-Dist: fqdn; extra == 'format-nongpl'
Requires-Dist: idna; extra == 'format-nongpl'
Requires-Dist: isoduration; extra == 'format-nongpl'
Requires-Dist: jsonpointer>1.13; extra == 'format-nongpl'
Requires-Dist: rfc3339-validator; extra == 'format-nongpl'
Requires-Dist: rfc3986-validator>0.1.0; extra == 'format-nongpl'
Requires-Dist: uri-template; extra == 'format-nongpl'
Requires-Dist: webcolors>=1.11; extra == 'format-nongpl'
